{
  "attributes": [
    {
      "default": "nil",
      "size": null,
      "type": "bigint",
      "source": "id",
      "references": null,
      "allow_nil?": false,
      "primary_key?": true,
      "generated?": true
    },
    {
      "default": "nil",
      "size": null,
      "type": "map",
      "source": "value",
      "references": null,
      "allow_nil?": true,
      "primary_key?": false,
      "generated?": false
    },
    {
      "default": "nil",
      "size": null,
      "type": "map",
      "source": "metadata",
      "references": null,
      "allow_nil?": true,
      "primary_key?": false,
      "generated?": false
    },
    {
      "default": "nil",
      "size": null,
      "type": "bigint",
      "source": "dimension_id",
      "references": {
        "name": "values_dimension_id_fkey",
        "table": "dimensions",
        "on_delete": null,
        "primary_key?": true,
        "multitenancy": {
          "global": null,
          "strategy": null,
          "attribute": null
        },
        "destination_attribute": "id",
        "on_update": null,
        "deferrable": false,
        "destination_attribute_default": null,
        "destination_attribute_generated": null
      },
      "allow_nil?": true,
      "primary_key?": false,
      "generated?": false
    }
  ],
  "table": "values",
  "hash": "908851E1C25B4474B1841C2B6514035D5887BAF66D530B4220D767C7F3CAB1A7",
  "identities": [],
  "repo": "Elixir.Numeri.Repo",
  "multitenancy": {
    "global": null,
    "strategy": null,
    "attribute": null
  },
  "custom_indexes": [],
  "base_filter": null,
  "custom_statements": [],
  "has_create_action": false
}