{
  "attributes": [
    {
      "default": "nil",
      "size": null,
      "type": "uuid",
      "source": "id",
      "references": null,
      "allow_nil?": false,
      "primary_key?": true,
      "generated?": false
    },
    {
      "default": "nil",
      "size": null,
      "type": "text",
      "source": "variable_id",
      "references": null,
      "allow_nil?": true,
      "primary_key?": false,
      "generated?": false
    },
    {
      "default": "nil",
      "size": null,
      "type": "text",
      "source": "text",
      "references": null,
      "allow_nil?": true,
      "primary_key?": false,
      "generated?": false
    },
    {
      "default": "nil",
      "size": null,
      "type": "bigint",
      "source": "order",
      "references": null,
      "allow_nil?": true,
      "primary_key?": false,
      "generated?": false
    },
    {
      "default": "nil",
      "size": null,
      "type": "boolean",
      "source": "elimination",
      "references": null,
      "allow_nil?": true,
      "primary_key?": false,
      "generated?": false
    },
    {
      "default": "nil",
      "size": null,
      "type": "boolean",
      "source": "time",
      "references": null,
      "allow_nil?": true,
      "primary_key?": false,
      "generated?": false
    }
  ],
  "table": "variables",
  "hash": "C039B8C7DA05CDE10761A069BE03F3577BAAE6021BD4F53AAEB4B5DC3A93E406",
  "identities": [
    {
      "name": "unique_variable",
      "keys": [
        "variable_id"
      ],
      "base_filter": null,
      "index_name": "variables_unique_variable_index"
    }
  ],
  "repo": "Elixir.Dbk.Repo",
  "custom_indexes": [],
  "base_filter": null,
  "custom_statements": [],
  "multitenancy": {
    "global": null,
    "strategy": null,
    "attribute": null
  },
  "has_create_action": true
}